<annotation>
	<folder>car_long</folder>
	<filename>36936.jpg</filename>
	<path>D:\python_work\car_number\1_Labeling\car_long\car_long\36936.jpg</path>
	<source>
		<database>Unknown</database>
	</source>
	<size>
		<width>472</width>
		<height>303</height>
		<depth>3</depth>
	</size>
	<segmented>0</segmented>
	<object>
		<name>number_plate</name>
		<pose>Unspecified</pose>
		<truncated>0</truncated>
		<difficult>0</difficult>
		<bndbox>
			<xmin>198</xmin>
			<ymin>151</ymin>
			<xmax>305</xmax>
			<ymax>181</ymax>
		</bndbox>
	</object>
</annotation>
